Metadata-Version: 2.1
Name: zz-test
Version: 0.0.3
Summary: zz test playground
Home-page: http://github.com/ffreemt/zz-test
Author: mikeee
License: MIT License
Download-URL: https://github.com/ffreemt/yeekit-tr-free/archive/v_003.tar.gz
Keywords: machine translation,free,scraping
Platform: UNKNOWN
Classifier: Development Status :: 3 - Alpha
Classifier: Intended Audience :: Developers
Classifier: Programming Language :: Python :: 3
Classifier: Programming Language :: Python :: 3.6
Classifier: License :: OSI Approved :: MIT License
